auto_tmux/__init__.py
auto_tmux-0.2.3.dist-info/LICENSE
auto_tmux-0.2.3.dist-info/METADATA
auto_tmux-0.2.3.dist-info/WHEEL
auto_tmux-0.2.3.dist-info/entry_points.txt
auto_tmux-0.2.3.dist-info/top_level.txt
auto_tmux-0.2.3.dist-info/RECORD
