Metadata-Version: 2.1
Name: auto-tmux
Version: 0.2.3
Summary: yet another tmux automation script that takes yaml
Author: Calacuda
Maintainer: Calacuda
License: MIT License
Project-URL: Repository, https://github.com/calacuda/auto-tmux
Classifier: Development Status :: 4 - Beta
Classifier: Intended Audience :: End Users/Desktop
Classifier: License :: OSI Approved :: MIT License
Classifier: Operating System :: POSIX :: Linux
Classifier: Programming Language :: Python :: 3.12
Classifier: Programming Language :: Python :: 3.11
Classifier: Programming Language :: Python :: 3.10
Classifier: Programming Language :: Python :: 3.9
Requires-Python: >=3.9
License-File: LICENSE
Requires-Dist: tqdm
Requires-Dist: pyaml
Requires-Dist: libtmux
